pocket_newsletter/__main__.py
pocket_newsletter/main.py
pocket_newsletter-0.2.0.dist-info/LICENSE
pocket_newsletter-0.2.0.dist-info/WHEEL
pocket_newsletter-0.2.0.dist-info/entry_points.txt
pocket_newsletter-0.2.0.dist-info/METADATA
pocket_newsletter-0.2.0.dist-info/RECORD
